protosym/__init__.py
protosym/__main__.py
protosym/py.typed
protosym/core/__init__.py
protosym/core/atom.py
protosym/core/differentiate.py
protosym/core/evaluate.py
protosym/core/exceptions.py
protosym/core/sym.py
protosym/core/tree.py
protosym/simplecas/__init__.py
protosym/simplecas/exceptions.py
protosym/simplecas/expr.py
protosym/simplecas/functions.py
protosym/simplecas/lambdification.py
protosym/simplecas/matrix.py
protosym/simplecas/sympy_conversions.py
protosym-0.0.6.dist-info/METADATA
protosym-0.0.6.dist-info/WHEEL
protosym-0.0.6.dist-info/licenses/LICENSE.rst
protosym-0.0.6.dist-info/RECORD
