Metadata-Version: 2.3
Name: protosym
Version: 0.0.6
Summary: ProtoSym
Author-email: Oscar Benjamin <oscar.j.benjamin@gmail.com>
License-Expression: BSD-3-Clause
License-File: LICENSE.rst
Classifier: License :: OSI Approved :: BSD License
Classifier: Programming Language :: Python :: 3.8
Classifier: Programming Language :: Python :: 3.9
Classifier: Programming Language :: Python :: 3.10
Classifier: Programming Language :: Python :: 3.11
Classifier: Programming Language :: Python :: 3.12
Requires-Python: >=3.8
Provides-Extra: all
Requires-Dist: llvmlite; extra == 'all'
Requires-Dist: numpy; extra == 'all'
Requires-Dist: sympy; extra == 'all'
